dag_json.py
dag_json-0.3.dist-info/LICENSE
dag_json-0.3.dist-info/METADATA
dag_json-0.3.dist-info/WHEEL
dag_json-0.3.dist-info/top_level.txt
dag_json-0.3.dist-info/RECORD
