Metadata-Version: 2.1
Name: dag-json
Version: 0.3
Summary: Python implementation of the IPLD DAG-JSON codec
Author-email: Ryan Barrett <dag-json@ryanb.org>
Project-URL: Homepage, https://github.com/snarfed/dag-json
Keywords: DAG-JSON,IPLD,codec,CID
Classifier: Programming Language :: Python :: 3
Classifier: Programming Language :: Python :: 3.7
Classifier: License :: Public Domain
Classifier: Operating System :: OS Independent
Classifier: Intended Audience :: Developers
Classifier: Development Status :: 3 - Alpha
Classifier: Topic :: Software Development :: Libraries :: Python Modules
Requires-Python: >=3.7
License-File: LICENSE
Requires-Dist: multiformats >=0.3.1.post4
Provides-Extra: tests
Requires-Dist: python-testmark >=1.0 ; extra == 'tests'
